wiremapper/__init__.py
wiremapper/__main__.py
wiremapper/discover.py
wiremapper/preferences.py
wiremapper/quicktest.py
wiremapper/wiremap.py
wiremapper/wiremapper.glade
wiremapper/wiremapper.gresource
wiremapper/block/ber.py
wiremapper/block/block.py
wiremapper/block/dhcp.py
wiremapper/block/link.py
wiremapper/block/poe.py
wiremapper/block/tdr.py
wiremapper/block/wiremap.py
wiremapper-0.8.0.dist-info/METADATA
wiremapper-0.8.0.dist-info/WHEEL
wiremapper-0.8.0.dist-info/entry_points.txt
wiremapper-0.8.0.dist-info/top_level.txt
wiremapper-0.8.0.dist-info/zip-safe
wiremapper-0.8.0.dist-info/RECORD
